zodchy_notations/__init__.py
zodchy_notations/query/__init__.py
zodchy_notations/query/math.py
zodchy_notations-0.1.6.dist-info/METADATA
zodchy_notations-0.1.6.dist-info/WHEEL
zodchy_notations-0.1.6.dist-info/RECORD
