Metadata-Version: 2.1
Name: zodchy-notations
Version: 0.1.6
Summary: 
Home-page: https://github.com/smairon/zodchy-notations
Author: Smairon
Author-email: man@smairon.ru
Requires-Python: >=3.11,<4.0
Classifier: Programming Language :: Python :: 3
Classifier: Programming Language :: Python :: 3.11
Classifier: Programming Language :: Python :: 3.12
Requires-Dist: python-dateutil (>=2.9.0,<3.0.0)
Requires-Dist: zodchy (>=0.5.0,<0.6.0)
Project-URL: Repository, https://github.com/smairon/zodchy-notations
